aws_s3_sdk-1.0.0.dist-info/licenses/LICENSE
awss3/__init__.py
awss3/api_helper.py
awss3/awss_3_client.py
awss3/configuration.py
awss3/controllers/__init__.py
awss3/controllers/accelerate_controller.py
awss3/controllers/acl_controller.py
awss3/controllers/analytics_controller.py
awss3/controllers/base_controller.py
awss3/controllers/buckets_controller.py
awss3/controllers/cors_controller.py
awss3/controllers/encryption_controller.py
awss3/controllers/inventory_controller.py
awss3/controllers/legal_hold_controller.py
awss3/controllers/lifecycle_controller.py
awss3/controllers/location_controller.py
awss3/controllers/lock_controller.py
awss3/controllers/logging_controller.py
awss3/controllers/metrics_controller.py
awss3/controllers/misc_controller.py
awss3/controllers/notifications_controller.py
awss3/controllers/objects_controller.py
awss3/controllers/payments_controller.py
awss3/controllers/policy_controller.py
awss3/controllers/public_access_block_controller.py
awss3/controllers/replication_controller.py
awss3/controllers/retention_controller.py
awss3/controllers/tagging_controller.py
awss3/controllers/torrent_controller.py
awss3/controllers/uploads_controller.py
awss3/controllers/versioning_controller.py
awss3/controllers/versions_controller.py
awss3/controllers/website_controller.py
awss3/exceptions/__init__.py
awss3/exceptions/api_exception.py
awss3/exceptions/error_exception.py
awss3/http/__init__.py
awss3/http/http_call_back.py
awss3/http/http_method_enum.py
awss3/http/http_request.py
awss3/http/http_response.py
awss3/models/__init__.py
awss3/models/access_control_list.py
awss3/models/access_control_list_1.py
awss3/models/access_control_policy.py
awss3/models/access_control_policy_1.py
awss3/models/arn_like.py
awss3/models/bucket.py
awss3/models/bucket_policy.py
awss3/models/bucket_policy_request.py
awss3/models/buckets.py
awss3/models/condition.py
awss3/models/contents.py
awss3/models/grant.py
awss3/models/grant_1.py
awss3/models/grantee.py
awss3/models/grantee_1.py
aws_s3_sdk-1.0.0.dist-info/METADATA
aws_s3_sdk-1.0.0.dist-info/WHEEL
aws_s3_sdk-1.0.0.dist-info/top_level.txt
aws_s3_sdk-1.0.0.dist-info/RECORD
